kahi_scimago_sources/Kahi_scimago_sources.py
kahi_scimago_sources/__init__.py
kahi_scimago_sources/_version.py
Kahi_scimago_sources-0.1.0b0.dist-info/LICENSE
Kahi_scimago_sources-0.1.0b0.dist-info/METADATA
Kahi_scimago_sources-0.1.0b0.dist-info/WHEEL
Kahi_scimago_sources-0.1.0b0.dist-info/top_level.txt
Kahi_scimago_sources-0.1.0b0.dist-info/RECORD
