Metadata-Version: 2.1
Name: Kahi-scimago-sources
Version: 0.1.0b0
Summary: Kahi plugin for scimago sources
Home-page: https://github.com/colav/Kahi_plugins
Author: Colav
Author-email: colav@udea.edu.co
License: BSD
License-File: LICENSE
Requires-Dist: kahi
Requires-Dist: pymongo
Requires-Dist: datetime
Requires-Dist: iso3166
